TradeMaster/TradeSync.py
TradeMaster/__init__.py
TradeMaster/base_validation/__init__.py
TradeMaster/base_validation/_orderValidation.py
TradeMaster/base_validation/checksum.py
TradeMaster/base_validation/file_read.py
TradeMaster/base_validation/timestamp.py
TradeMaster/network/__init__.py
TradeMaster/network/api_client.py
TradeMaster/network/device_identifier.py
config/__init__.py
config/config.py
config/settings.py
utility/__init__.py
utility/library.py
Ant_A3_tradehub_sdk_test-1.0.1.dist-info/METADATA
Ant_A3_tradehub_sdk_test-1.0.1.dist-info/WHEEL
Ant_A3_tradehub_sdk_test-1.0.1.dist-info/top_level.txt
Ant_A3_tradehub_sdk_test-1.0.1.dist-info/RECORD
